baselines/__init__.py
baselines/evaluate_baseline.py
baselines/generate_crystal_knowledge.py
baselines/generate_rainier_knowledge.py
baselines/prompts.py
baselines/rbr_retriever/__init__.py
baselines/rbr_retriever/create_index.py
baselines/rbr_retriever/retriever_inference.py
baselines/rbr_retriever/train.py
baselines/utils/__init__.py
baselines/utils/data_utils.py
baselines/utils/metric_utils.py
baselines/utils/model_utils.py
baselines/utils/prompt_utils.py
baselines/utils/stdout_utils.py
zebra/__init__.py
zebra/pipeline.py
zebra/version.py
zebra/data/__init__.py
zebra/data/objects.py
zebra/prompts/__init__.py
zebra/prompts/prompts.py
zebra/utils/__init__.py
zebra/utils/data_utils.py
zebra/utils/metric_utils.py
zebra/utils/model_utils.py
zebra/utils/prompt_utils.py
zebra/utils/stdout_utils.py
zebra_qa-1.0.1.dist-info/LICENSE
zebra_qa-1.0.1.dist-info/METADATA
zebra_qa-1.0.1.dist-info/WHEEL
zebra_qa-1.0.1.dist-info/top_level.txt
zebra_qa-1.0.1.dist-info/RECORD
