Metadata-Version: 2.1
Name: zebra-qa
Version: 1.0.1
Summary: ZEBRA: Zero-Shot Example-Based Retrieval Augmentation for Commonsense Question Answering
Home-page: https://github.com/sapienzanlp/zebra
Author: Francesco Molfese
Author-email: molfesefrancesco@gmail.com
License: Creative Commons Attribution-NonCommercial-ShareAlike 4.0
Keywords: NLP Sapienza sapienzanlp deep learning transformer pytorch retriever question answering commonsense large language models
Classifier: Intended Audience :: Science/Research
Classifier: Programming Language :: Python :: 3
Classifier: Topic :: Scientific/Engineering :: Artificial Intelligence
Requires-Python: >=3.10
License-File: LICENSE
Requires-Dist: torch==2.2.0
Requires-Dist: transformers==4.42.4
Requires-Dist: accelerate==0.30.1
Requires-Dist: datasets==2.16.1
Requires-Dist: rich==13.7.1
Requires-Dist: scikit-learn==1.4.2
Requires-Dist: tiktoken==0.7.0
Requires-Dist: pytest==8.2.2
Requires-Dist: bitsandbytes==0.43.3
Requires-Dist: lightning==2.2.5
Requires-Dist: hydra-core==1.3.2
Requires-Dist: hydra-colorlog==1.2.0
Requires-Dist: wandb==0.16.6
Requires-Dist: art==6.1
Requires-Dist: pprintpp==0.4.0
Requires-Dist: colorama==0.4.6
Requires-Dist: jsonlines==4.0.0
Requires-Dist: loguru==0.7.2
Requires-Dist: goldenretriever-core==0.9.4
Requires-Dist: setuptools==75.1.0
Requires-Dist: twine==5.1.1
Requires-Dist: flash-attn==2.5.9.post1
